LICENSE.txt
MANIFEST.in
README.rst
setup.py
aldryn_disqus/__init__.py
aldryn_disqus/cms_plugins.py
aldryn_disqus/models.py
aldryn_disqus.egg-info/PKG-INFO
aldryn_disqus.egg-info/SOURCES.txt
aldryn_disqus.egg-info/dependency_links.txt
aldryn_disqus.egg-info/not-zip-safe
aldryn_disqus.egg-info/pbr.json
aldryn_disqus.egg-info/top_level.txt
aldryn_disqus/locale/de/LC_MESSAGES/django.mo
aldryn_disqus/locale/de/LC_MESSAGES/django.po
aldryn_disqus/locale/en/LC_MESSAGES/django.mo
aldryn_disqus/locale/en/LC_MESSAGES/django.po
aldryn_disqus/locale/fr/LC_MESSAGES/django.mo
aldryn_disqus/locale/fr/LC_MESSAGES/django.po
aldryn_disqus/locale/it/LC_MESSAGES/django.mo
aldryn_disqus/locale/it/LC_MESSAGES/django.po
aldryn_disqus/locale/ja/LC_MESSAGES/django.mo
aldryn_disqus/locale/ja/LC_MESSAGES/django.po
aldryn_disqus/migrations/0001_initial.py
aldryn_disqus/migrations/__init__.py
aldryn_disqus/south_migrations/0001_initial.py
aldryn_disqus/south_migrations/0002_cmsplugin_table_name_magic_removal.py
aldryn_disqus/south_migrations/__init__.py
aldryn_disqus/templates/aldryn_disqus/disqus.html