Metadata-Version: 1.1
Name: aldryn-disqus
Version: 1.0.0
Summary: Allows embeding Disqus threads into the site
Home-page: https://github.com/aldryn/aldryn-disqus
Author: Divio AG
Author-email: info@divio.ch
License: LICENSE.txt
Platform: OS Independent
Classifier: Development Status :: 5 - Production/Stable
Classifier: Environment :: Web Environment
Classifier: Framework :: Django
Classifier: Intended Audience :: Developers
Classifier: License :: OSI Approved :: BSD License
Classifier: Operating System :: OS Independent
Classifier: Programming Language :: Python
Classifier: Topic :: Communications
Classifier: Topic :: Internet :: WWW/HTTP :: Dynamic Content
Classifier: Programming Language :: Python :: 2.6
Classifier: Programming Language :: Python :: 2.7
